lastearthquake/__init__.py
Monitoring_IndonesiaLastEarthquake-0.0.4.dist-info/LICENSE
Monitoring_IndonesiaLastEarthquake-0.0.4.dist-info/METADATA
Monitoring_IndonesiaLastEarthquake-0.0.4.dist-info/WHEEL
Monitoring_IndonesiaLastEarthquake-0.0.4.dist-info/top_level.txt
Monitoring_IndonesiaLastEarthquake-0.0.4.dist-info/RECORD
