Metadata-Version: 2.1
Name: Monitoring-IndonesiaLastEarthquake
Version: 0.0.4
Summary: This package will get the latest earthquake from Indonesia Meteorological, Climatological, and Geophysical Agency (BMKG).
Home-page: https://github.com/Anugrahibra
Author: Anugrah Ibra
Author-email: anugrahibra88@gmail.com
Project-URL: Github, https://github.com/Anugrahibra/Monitoring-IndonesiaLastEarthquake
Classifier: Programming Language :: Python :: 3
Classifier: License :: OSI Approved :: GNU General Public License v2 or later (GPLv2+)
Classifier: Operating System :: OS Independent
Classifier: Development Status :: 5 - Production/Stable
Requires-Python: >=3.6
License-File: LICENSE
Requires-Dist: beautifulsoup4
Requires-Dist: requests
